pytest_deepassert/__init__.py
pytest_deepassert/api.py
pytest_deepassert/diff_report/__init__.py
pytest_deepassert/diff_report/compare_helpers_deepdiff_operator.py
pytest_deepassert/diff_report/report_generator.py
pytest_deepassert/plugin/__init__.py
pytest_deepassert/plugin/hook.py
pytest_deepassert-0.3.0.dist-info/METADATA
pytest_deepassert-0.3.0.dist-info/WHEEL
pytest_deepassert-0.3.0.dist-info/entry_points.txt
pytest_deepassert-0.3.0.dist-info/licenses/LICENSE
pytest_deepassert-0.3.0.dist-info/RECORD
