Metadata-Version: 2.4
Name: pytest-deepassert
Version: 0.3.0
Summary: A pytest plugin for enhanced assertion reporting with detailed diffs
Project-URL: Homepage, https://github.com/alexkuzmik/pytest-deepassert
Project-URL: Repository, https://github.com/alexkuzmik/pytest-deepassert
Project-URL: Issues, https://github.com/alexkuzmik/pytest-deepassert/issues
Author-email: Alexander Kuzmik <alexander.kuzmik99@gmail.com>
License: MIT
License-File: LICENSE
Keywords: assertions,debugging,diff,plugin,pytest,testing
Classifier: Development Status :: 3 - Alpha
Classifier: Framework :: Pytest
Classifier: Intended Audience :: Developers
Classifier: License :: OSI Approved :: MIT License
Classifier: Programming Language :: Python :: 3
Classifier: Programming Language :: Python :: 3.8
Classifier: Programming Language :: Python :: 3.9
Classifier: Programming Language :: Python :: 3.10
Classifier: Programming Language :: Python :: 3.11
Classifier: Programming Language :: Python :: 3.12
Classifier: Programming Language :: Python :: 3.13
Classifier: Topic :: Software Development :: Debuggers
Classifier: Topic :: Software Development :: Testing
Requires-Python: >=3.8
Requires-Dist: deepdiff>=6.0.0
Requires-Dist: pytest>=7.0.0
Requires-Dist: typing-extensions>=4.0.0
Provides-Extra: dev
Requires-Dist: pre-commit>=3.0.0; extra == 'dev'
Requires-Dist: pytest-cov>=4.0.0; extra == 'dev'
Requires-Dist: pytest-xdist>=3.0.0; extra == 'dev'
Requires-Dist: pytest>=6.0.0; extra == 'dev'
